gitlab_ci_mr_tested.py
gitlab_ci_mr_tested-1.7.dist-info/LICENSE
gitlab_ci_mr_tested-1.7.dist-info/METADATA
gitlab_ci_mr_tested-1.7.dist-info/WHEEL
gitlab_ci_mr_tested-1.7.dist-info/entry_points.txt
gitlab_ci_mr_tested-1.7.dist-info/top_level.txt
gitlab_ci_mr_tested-1.7.dist-info/RECORD
