Metadata-Version: 2.1
Name: gitlab-ci-mr-tested
Version: 1.7
Summary: Utility for use in gitlab ci to check merge requests have been marked tested
Home-page: https://gitlab.com/alelec/gitlab-ci-mr-tested
Author: Andrew Leech
Author-email: andrew@alelec.net
License: MIT
Platform: UNKNOWN
License-File: LICENSE
Requires-Dist: python-gitlab
Requires-Dist: click
